mk_scaffold/__init__.py
mk_scaffold/__main__.py
mk_scaffold/answers.py
mk_scaffold/constants.py
mk_scaffold/environment.py
mk_scaffold/extensions.py
mk_scaffold/includes.py
mk_scaffold/questions.py
mk_scaffold/utils.py
mk_scaffold/cli/__init__.py
mk_scaffold/cli/clone.py
mk_scaffold/cli/validate.py
mk_scaffold/template/__init__.py
mk_scaffold/template/directory.py
mk_scaffold/template/git.py
mk_scaffold/testing/__init__.py
mk_scaffold/validators/allowed.py
mk_scaffold/validators/boolean.py
mk_scaffold/validators/default.py
mk_scaffold/validators/max_length.py
mk_scaffold/validators/min_length.py
mk_scaffold/validators/nullable.py
mk_scaffold/validators/vartype.py
mk_scaffold-1.6.0.dist-info/LICENSE
mk_scaffold-1.6.0.dist-info/METADATA
mk_scaffold-1.6.0.dist-info/WHEEL
mk_scaffold-1.6.0.dist-info/entry_points.txt
mk_scaffold-1.6.0.dist-info/top_level.txt
mk_scaffold-1.6.0.dist-info/zip-safe
mk_scaffold-1.6.0.dist-info/RECORD
