Metadata-Version: 2.1
Name: mk-scaffold
Version: 1.6.0
Summary: A cookiecutter clone. A command-line utility that creates projects from templates.
Author-email: Julien Lecomte <julien@lecomte.at>
License: MIT
Project-URL: Homepage, https://gitlab.com/cappysan/mk-scaffold
Project-URL: Documentation, https://mk-scaffold.docs.cappysan.dev/
Project-URL: Source code, https://gitlab.com/cappysan/mk-scaffold
Project-URL: Bug tracker, https://gitlab.com/cappysan/mk-scaffold/-/issues
Classifier: License :: OSI Approved :: MIT License
Classifier: Intended Audience :: Developers
Classifier: Development Status :: 5 - Production/Stable
Classifier: Programming Language :: Python :: 3 :: Only
Classifier: Programming Language :: Python :: 3.9
Classifier: Programming Language :: Python :: 3.10
Classifier: Programming Language :: Python :: 3.11
Classifier: Programming Language :: Python :: 3.12
Requires-Python: >=3.9
License-File: LICENSE
Requires-Dist: cerberus
Requires-Dist: imxdparser
Requires-Dist: jinja2-time
Requires-Dist: jinjazzle>=1.2.0
Requires-Dist: prompt-toolkit
Requires-Dist: python-slugify
Requires-Dist: pyyaml
Requires-Dist: requests
Requires-Dist: torxtools
Provides-Extra: dev
